vaddiocameras/__init__.py
vaddiocameras-1.0.2.dist-info/LICENSE
vaddiocameras-1.0.2.dist-info/METADATA
vaddiocameras-1.0.2.dist-info/WHEEL
vaddiocameras-1.0.2.dist-info/top_level.txt
vaddiocameras-1.0.2.dist-info/RECORD
