Metadata-Version: 2.1
Name: vaddiocameras
Version: 1.0.2
Summary: retrieve info from Vaddio camera telnet
Home-page: https://github.com/logantv/vaddiocameras
Author: Logan Vaughn
License: UNKNOWN
Project-URL: Bug Tracker, https://github.com/logantv/vaddiocameras/issues
Platform: UNKNOWN
Classifier: Programming Language :: Python :: 3
Classifier: License :: OSI Approved :: MIT License
Classifier: Operating System :: OS Independent
Requires-Python: >=3.6
Requires-Dist: amxtelnet
Requires-Dist: amxtoexcel
